CHANGES.txt
LICENSE.txt
MANIFEST.in
README.txt
setup.py
js/__init__.py
js.jquery_globalize.egg-info/PKG-INFO
js.jquery_globalize.egg-info/SOURCES.txt
js.jquery_globalize.egg-info/dependency_links.txt
js.jquery_globalize.egg-info/entry_points.txt
js.jquery_globalize.egg-info/namespace_packages.txt
js.jquery_globalize.egg-info/not-zip-safe
js.jquery_globalize.egg-info/requires.txt
js.jquery_globalize.egg-info/top_level.txt
js/jquery_globalize/__init__.py
js/jquery_globalize/test_jquery_globalize.txt
js/jquery_globalize/resources/globalize.js
js/jquery_globalize/resources/cultures/globalize.culture.af-ZA.js
js/jquery_globalize/resources/cultures/globalize.culture.af.js
js/jquery_globalize/resources/cultures/globalize.culture.am-ET.js
js/jquery_globalize/resources/cultures/globalize.culture.am.js
js/jquery_globalize/resources/cultures/globalize.culture.ar-AE.js
js/jquery_globalize/resources/cultures/globalize.culture.ar-BH.js
js/jquery_globalize/resources/cultures/globalize.culture.ar-DZ.js
js/jquery_globalize/resources/cultures/globalize.culture.ar-EG.js
js/jquery_globalize/resources/cultures/globalize.culture.ar-IQ.js
js/jquery_globalize/resources/cultures/globalize.culture.ar-JO.js
js/jquery_globalize/resources/cultures/globalize.culture.ar-KW.js
js/jquery_globalize/resources/cultures/globalize.culture.ar-LB.js
js/jquery_globalize/resources/cultures/globalize.culture.ar-LY.js
js/jquery_globalize/resources/cultures/globalize.culture.ar-MA.js
js/jquery_globalize/resources/cultures/globalize.culture.ar-OM.js
js/jquery_globalize/resources/cultures/globalize.culture.ar-QA.js
js/jquery_globalize/resources/cultures/globalize.culture.ar-SA.js
js/jquery_globalize/resources/cultures/globalize.culture.ar-SY.js
js/jquery_globalize/resources/cultures/globalize.culture.ar-TN.js
js/jquery_globalize/resources/cultures/globalize.culture.ar-YE.js
js/jquery_globalize/resources/cultures/globalize.culture.ar.js
js/jquery_globalize/resources/cultures/globalize.culture.arn-CL.js
js/jquery_globalize/resources/cultures/globalize.culture.arn.js
js/jquery_globalize/resources/cultures/globalize.culture.as-IN.js
js/jquery_globalize/resources/cultures/globalize.culture.as.js
js/jquery_globalize/resources/cultures/globalize.culture.az-Cyrl-AZ.js
js/jquery_globalize/resources/cultures/globalize.culture.az-Cyrl.js
