Metadata-Version: 1.0
Name: js.jquery-globalize
Version: 0.1.0a2
Summary: Fanstatic packaging of jquery globalize
Home-page: UNKNOWN
Author: Fanstatic Developers
Author-email: fanstatic@googlegroups.com
License: MIT
Platform: UNKNOWN
